aws_kommandos/__init__.py
aws_kommandos/ami_kommandos.py
aws_kommandos/command_line.py
aws_kommandos/dns_kommandos.py
aws_kommandos/ec2_instance_kommandos.py
aws_kommandos/firewall_rule_request.py
aws_kommandos/kommandos.py
aws_kommandos/s3_bucket_kommandos.py
aws_kommandos/security_groups_kommandos.py
aws_kommandos/ssh_key_pairs_kommandos.py
aws_kommandos-1.0.14.dist-info/LICENSE
aws_kommandos-1.0.14.dist-info/METADATA
aws_kommandos-1.0.14.dist-info/WHEEL
aws_kommandos-1.0.14.dist-info/entry_points.txt
aws_kommandos-1.0.14.dist-info/top_level.txt
aws_kommandos-1.0.14.dist-info/RECORD
