Metadata-Version: 2.1
Name: aws-kommandos
Version: 1.0.14
Summary: Advisory Infrastructure Setup Toolset - The Python Package
Home-page: https://github.com/derstolz/aws-kommandos
Author: totekuh
Author-email: totekuh@protonmail.com
Project-URL: Bug Reports, https://github.com/derstolz/aws-kommandos/issues
Project-URL: Source, https://github.com/derstolz/aws-kommandos
Keywords: pentest,red-team,aws
Classifier: Development Status :: 5 - Production/Stable
Classifier: Environment :: Console
Classifier: Intended Audience :: Information Technology
Classifier: Intended Audience :: System Administrators
Classifier: Intended Audience :: Other Audience
Classifier: License :: OSI Approved :: MIT License
Classifier: Operating System :: POSIX :: Linux
Classifier: Programming Language :: Python :: 3
Classifier: Programming Language :: Python :: 3.6
Classifier: Programming Language :: Python :: 3.7
Classifier: Programming Language :: Python :: 3.8
Classifier: Programming Language :: Python :: 3.9
Classifier: Programming Language :: Python :: 3 :: Only
Requires-Python: >=3.6, <4
License-File: LICENSE
Requires-Dist: boto3
Requires-Dist: termcolor
Requires-Dist: pandas
Requires-Dist: numpy
